apricatewrapper/__init__.py
apricatewrapper/apricate_api.py
apricatewrapper/endpoints/__init__.py
apricatewrapper/endpoints/assistants.py
apricatewrapper/endpoints/caravans.py
apricatewrapper/endpoints/farms.py
apricatewrapper/endpoints/information.py
apricatewrapper/endpoints/locations.py
apricatewrapper/endpoints/magic.py
apricatewrapper/endpoints/markets.py
apricatewrapper/endpoints/metrics.py
apricatewrapper/endpoints/plants.py
apricatewrapper/endpoints/plots.py
apricatewrapper/endpoints/quests.py
apricatewrapper/endpoints/users.py
apricatewrapper/endpoints/warehouses.py
apricatewrapper-0.1.0.1.dist-info/LICENSE
apricatewrapper-0.1.0.1.dist-info/METADATA
apricatewrapper-0.1.0.1.dist-info/WHEEL
apricatewrapper-0.1.0.1.dist-info/top_level.txt
apricatewrapper-0.1.0.1.dist-info/RECORD
