Metadata-Version: 2.1
Name: apricatewrapper
Version: 0.1.0.1
Summary: A wrapper around the Apricate.io API in python
Home-page: https://github.com/Denmads/ApricateIO-Wrapper
Author: Mads Jensen
Author-email: 
License: UNKNOWN
Platform: UNKNOWN
Classifier: Programming Language :: Python :: 3.9
Classifier: License :: OSI Approved :: MIT License
License-File: LICENSE
Requires-Dist: requests (>=2.27.1)
